rashifal/__init__.py
rashifal/func.py
rashifal-0.0.1.dist-info/METADATA
rashifal-0.0.1.dist-info/WHEEL
rashifal-0.0.1.dist-info/top_level.txt
rashifal-0.0.1.dist-info/RECORD
