Metadata-Version: 2.1
Name: rashifal
Version: 0.0.1
Summary: Nepali zodiac sign
Home-page: UNKNOWN
Author: James Kulu
Author-email: jameskulu55@gmail.com
License: UNKNOWN
Keywords: python,zodiac,rashi
Platform: UNKNOWN
Classifier: Development Status :: 1 - Planning
Classifier: Intended Audience :: Developers
Classifier: Programming Language :: Python :: 3
Classifier: Operating System :: Unix
Classifier: Operating System :: MacOS :: MacOS X
Classifier: Operating System :: Microsoft :: Windows
